capetools/__init__.py
capetools/_nbdev.py
capetools/imports.py
capetools/modelling/__init__.py
capetools/modelling/mybifacialvf.py
capetools/modelling/mypvfactors.py
capetools/utils/__init__.py
capetools/utils/core.py
capetools/utils/matlab_io.py
capetools/utils/missing.py
capetools/utils/pandas_hacks.py
capetools/utils/plot.py
capetools/utils/tmy.py
capetools-1.0.2.dist-info/LICENSE
capetools-1.0.2.dist-info/METADATA
capetools-1.0.2.dist-info/WHEEL
capetools-1.0.2.dist-info/entry_points.txt
capetools-1.0.2.dist-info/top_level.txt
capetools-1.0.2.dist-info/RECORD
