Metadata-Version: 2.1
Name: capetools
Version: 1.0.2
Summary: Basic set of python tools
Home-page: https://github.com/tcapelle/capetools
Author: Thomas Capelle
Author-email: tcapelle@protonmail.com
License: Apache Software License 2.0
Keywords: timeseries jupyter modelling photovoltacis
Platform: UNKNOWN
Classifier: Development Status :: 4 - Beta
Classifier: Intended Audience :: Developers
Classifier: License :: OSI Approved :: Apache Software License
Classifier: Natural Language :: English
Classifier: Programming Language :: Python :: 3.6
Classifier: Programming Language :: Python :: 3.7
Classifier: Programming Language :: Python :: 3.8
Requires-Python: >=3.6
Requires-Dist: pvlib (>-=0.7)
Requires-Dist: pandas (>=0.25)
Requires-Dist: pvfactors (>=1.4)
Requires-Dist: pyarrow
Requires-Dist: fastcore
Requires-Dist: numpy
Requires-Dist: matplotlib
Requires-Dist: jupyter
Requires-Dist: sklearn
Requires-Dist: fastprogress
Requires-Dist: hdf5storage
Requires-Dist: tables
